personal_graph/__init__.py
personal_graph/clients.py
personal_graph/database/__init__.py
personal_graph/database/db.py
personal_graph/database/postgres/README.md
personal_graph/database/redis/README.md
personal_graph/database/sqlite/__init__.py
personal_graph/database/sqlite/raw-queries/delete-edge.sql
personal_graph/database/sqlite/raw-queries/delete-node.sql
personal_graph/database/sqlite/raw-queries/insert-edge.sql
personal_graph/database/sqlite/raw-queries/insert-node.sql
personal_graph/database/sqlite/raw-queries/schema.sql
personal_graph/database/sqlite/raw-queries/search-edge-by-rowid.sql
personal_graph/database/sqlite/raw-queries/search-edges-inbound.sql
personal_graph/database/sqlite/raw-queries/search-edges-outbound.sql
personal_graph/database/sqlite/raw-queries/search-edges.sql
personal_graph/database/sqlite/raw-queries/search-node-by-rowid.sql
personal_graph/database/sqlite/raw-queries/search-node.template
personal_graph/database/sqlite/raw-queries/search-where.template
personal_graph/database/sqlite/raw-queries/traverse.template
personal_graph/database/sqlite/raw-queries/update-node.sql
personal_graph/database/sqlite/sqlite.py
personal_graph/database/tursodb/__init__.py
personal_graph/database/tursodb/raw-queries/delete-edge.sql
personal_graph/database/tursodb/raw-queries/delete-node.sql
personal_graph/database/tursodb/raw-queries/insert-edge.sql
personal_graph/database/tursodb/raw-queries/insert-node.sql
personal_graph/database/tursodb/raw-queries/schema.sql
personal_graph/database/tursodb/raw-queries/search-edge-by-rowid.sql
personal_graph/database/tursodb/raw-queries/search-edges-inbound.sql
personal_graph/database/tursodb/raw-queries/search-edges-outbound.sql
personal_graph/database/tursodb/raw-queries/search-edges.sql
personal_graph/database/tursodb/raw-queries/search-node-by-rowid.sql
personal_graph/database/tursodb/raw-queries/search-node.template
personal_graph/database/tursodb/raw-queries/search-where.template
personal_graph-2.2.dist-info/LICENSE
personal_graph-2.2.dist-info/METADATA
personal_graph-2.2.dist-info/WHEEL
personal_graph-2.2.dist-info/RECORD
