Metadata-Version: 2.1
Name: personal-graph
Version: 2.2
Summary: Graph database in LibSQL
License: MIT
Author: Anubhuti Bhardwaj
Author-email: anubhutibhardwaj11@gmail.com
Requires-Python: >=3.11,<4.0
Classifier: License :: OSI Approved :: MIT License
Classifier: Programming Language :: Python :: 3
Classifier: Programming Language :: Python :: 3.11
Classifier: Programming Language :: Python :: 3.12
Provides-Extra: scrollable-textbox
Provides-Extra: turso
Requires-Dist: dspy-ai (==2.3.0)
Requires-Dist: fastapi (>=0.110.0,<0.111.0)
Requires-Dist: graphviz (>=0.20.1,<0.21.0)
Requires-Dist: instructor (>=1.2.2,<2.0.0)
Requires-Dist: jinja2 (>=3.1.3,<4.0.0)
Requires-Dist: litellm (>=1.35.26,<2.0.0)
Requires-Dist: networkx[default] (>=3.3,<4.0)
Requires-Dist: ollama (>=0.2.0,<0.3.0)
Requires-Dist: openai (>=1.14.2,<2.0.0)
Requires-Dist: pytest (>=8.1.1,<9.0.0)
Requires-Dist: pytest-mock (>=3.14.0,<4.0.0)
Requires-Dist: python-dotenv (>=1.0.1,<2.0.0)
Requires-Dist: sqlean-py (>=3.45.1,<4.0.0)
Requires-Dist: sqlite-vss (>=0.1.2,<0.2.0)
Requires-Dist: streamlit (>=1.33.0,<2.0.0)
Requires-Dist: types-decorator (>=5.1.8.20240310,<6.0.0.0)
Requires-Dist: types-pygments (>=2.17.0.20240310,<3.0.0.0)
Requires-Dist: uvicorn (>=0.29.0,<0.30.0)
Requires-Dist: vlite (>=0.2.7,<0.3.0)
